[
  {
    "id": "starter-nature",
    "name": "Nature Starter",
    "strategy": "Grow Bloom threats, stabilize with Guardian.",
    "difficulty": "easy",
    "strengths": [
      "synergy"
    ],
    "weaknesses": [
      "hate cards"
    ],
    "cards": {
      "rotr-c-bramblefox": 2,
      "rotr-c-elderfern": 2,
      "rotr-c-fernfox": 2,
      "rotr-c-groveowl": 2,
      "rotr-c-mossdrake": 2,
      "rotr-c-mossprig": 2,
      "rotr-c-rootling": 2,
      "rotr-c-saplingo": 2,
      "rotr-c-thornling": 2,
      "rotr-c-vinepup": 2,
      "rotr-c-twig-sprite": 2,
      "rotr-s-root-snare": 2,
      "rotr-s-bloom-draft": 2,
      "rotr-s-item-small-healing-salve": 2,
      "rotr-s-item-grove-restoration-brew": 2,
      "rotr-s-item-dormancy-revival-bloom": 2,
      "rotr-s-item-glowmoss-chew": 2,
      "rotr-comp-bramblefox": 2,
      "rotr-comp-elderfern": 2,
      "rotr-comp-fernfox": 2,
      "rotr-comp-groveowl": 2,
      "rotr-comp-mossdrake": 2,
      "rotr-comp-mossprig": 2,
      "rotr-comp-rootling": 2,
      "rotr-comp-saplingo": 2,
      "rotr-comp-thornling": 2,
      "rotr-comp-vinepup": 2,
      "rotr-e-keeper-s-satchel": 2,
      "rotr-e-moss-cloak": 2,
      "rotr-e-item-wooden-paw-guard": 2,
      "rotr-e-item-training-tail-ring": 2,
      "rotr-e-item-cloth-battle-harness": 2,
      "rotr-e-item-grove-twig-wand": 2
    },
    "recommendedUpgrades": [
      "rotr-c-bramblefox",
      "rotr-comp-bramblefox",
      "rotr-evo-bramblefox"
    ],
    "npcOwner": "elara",
    "lore": "Nature Starter is taught in the Living World before Keepers chase mythic hunts.",
    "archetype": "Riftbond midrange",
    "kind": "starter"
  },
  {
    "id": "starter-fire",
    "name": "Fire Aggro",
    "strategy": "Charge early, Empower finishers.",
    "difficulty": "easy",
    "strengths": [
      "fast pressure"
    ],
    "weaknesses": [
      "late game"
    ],
    "cards": {
      "rotr-c-ashwing": 2,
      "rotr-c-cindercub": 2,
      "rotr-c-cinderquill": 2,
      "rotr-c-craterhorn": 2,
      "rotr-c-emberfox": 2,
      "rotr-c-embernewt": 2,
      "rotr-c-furnacebeetle": 2,
      "rotr-c-lavaling": 2,
      "rotr-c-pyrespore": 2,
      "rotr-c-slagpup": 2,
      "rotr-c-ash-urchin": 2,
      "rotr-s-ember-spark": 2,
      "rotr-s-forge-temper": 2,
      "rotr-s-item-riftberry-tonic": 2,
      "rotr-s-item-emberheart-elixir": 2,
      "rotr-s-item-spark-healing-draught": 2,
      "rotr-s-item-ember-soothe-balm": 2,
      "rotr-comp-ashwing": 2,
      "rotr-comp-cindercub": 2,
      "rotr-comp-cinderquill": 2,
      "rotr-comp-craterhorn": 2,
      "rotr-comp-emberfox": 2,
      "rotr-comp-embernewt": 2,
      "rotr-comp-furnacebeetle": 2,
      "rotr-comp-lavaling": 2,
      "rotr-comp-pyrespore": 2,
      "rotr-comp-slagpup": 2,
      "rotr-e-keeper-s-satchel": 2,
      "rotr-e-ember-collar": 2,
      "rotr-e-item-training-tail-ring": 2,
      "rotr-e-item-cloth-battle-harness": 2,
      "rotr-e-item-ember-talons": 2,
      "rotr-e-item-ashfang-talons": 2
    },
    "recommendedUpgrades": [
      "rotr-c-ashwing",
      "rotr-comp-ashwing",
      "rotr-evo-ashwing"
    ],
    "npcOwner": "kael",
    "lore": "Fire Aggro is taught in the Living World before Keepers chase mythic hunts.",
    "archetype": "Aggro",
    "kind": "starter"
  },
  {
    "id": "starter-water",
    "name": "Water Healing",
    "strategy": "Ward, Overflow heals, sticky board.",
    "difficulty": "easy",
    "strengths": [
      "synergy"
    ],
    "weaknesses": [
      "hate cards"
    ],
    "cards": {
      "rotr-c-brinepaw": 2,
      "rotr-c-bubbloon": 2,
      "rotr-c-coralurge": 2,
      "rotr-c-frostbloom": 2,
      "rotr-c-frostfin": 2,
      "rotr-c-frostnip": 2,
      "rotr-c-glazehare": 2,
      "rotr-c-iciclepup": 2,
      "rotr-c-kelpwisp": 2,
      "rotr-c-moonray": 2,
      "rotr-c-pearlurk": 2,
      "rotr-c-rimewing": 2,
      "rotr-s-tide-mend": 2,
      "rotr-s-harbor-fog": 2,
      "rotr-s-item-moonwater-flask": 2,
      "rotr-s-item-fresh-water-flask": 2,
      "rotr-s-item-tide-mend-vial": 2,
      "rotr-s-item-frost-focus-brew": 2,
      "rotr-comp-brinepaw": 2,
      "rotr-comp-bubbloon": 2,
      "rotr-comp-coralurge": 2,
      "rotr-comp-frostbloom": 2,
      "rotr-comp-frostfin": 2,
      "rotr-comp-frostnip": 2,
      "rotr-comp-glazehare": 2,
      "rotr-comp-iciclepup": 2,
      "rotr-comp-kelpwisp": 2,
      "rotr-comp-moonray": 2,
      "rotr-comp-pearlurk": 2,
      "rotr-comp-rimewing": 2,
      "rotr-comp-snowglyph": 2,
      "rotr-comp-snowpuff": 2,
      "rotr-comp-sprayfin": 2,
      "rotr-comp-tideotter": 2
    },
    "recommendedUpgrades": [
      "rotr-c-brinepaw",
      "rotr-comp-brinepaw",
      "rotr-evo-brinepaw"
    ],
    "npcOwner": "brine",
    "lore": "Water Healing is taught in the Living World before Keepers chase mythic hunts.",
    "archetype": "Control-heal",
    "kind": "starter"
  },
  {
    "id": "starter-storm",
    "name": "Storm Control",
    "strategy": "Tempo Charge into card advantage.",
    "difficulty": "medium",
    "strengths": [
      "synergy"
    ],
    "weaknesses": [
      "hate cards"
    ],
    "cards": {
      "rotr-c-cloudleaper": 2,
      "rotr-c-commonspark": 2,
      "rotr-c-galekit": 2,
      "rotr-c-peakibex": 2,
      "rotr-c-sparkmoth": 2,
      "rotr-c-spirekite": 2,
      "rotr-c-staticat": 2,
      "rotr-c-stormmoth": 2,
      "rotr-c-thunderpaw": 2,
      "rotr-c-voltkit": 2,
      "rotr-c-windrift": 2,
      "rotr-c-static-mite": 2,
      "rotr-s-storm-sip": 2,
      "rotr-s-item-sparkfruit-juice": 2,
      "rotr-s-item-storm-energy-flask": 2,
      "rotr-s-item-storm-surge-sip": 2,
      "rotr-s-item-ancient-bell": 2,
      "rotr-comp-cloudleaper": 2,
      "rotr-comp-commonspark": 2,
      "rotr-comp-galekit": 2,
      "rotr-comp-peakibex": 2,
      "rotr-comp-sparkmoth": 2,
      "rotr-comp-spirekite": 2,
      "rotr-comp-staticat": 2,
      "rotr-comp-stormmoth": 2,
      "rotr-comp-thunderpaw": 2,
      "rotr-comp-voltkit": 2,
      "rotr-comp-windrift": 2,
      "rotr-e-keeper-s-satchel": 2,
      "rotr-e-storm-whistle": 2,
      "rotr-e-item-training-tail-ring": 2,
      "rotr-e-item-cloth-battle-harness": 2,
      "rotr-e-item-spark-tail-ring": 2
    },
    "recommendedUpgrades": [
      "rotr-c-cloudleaper",
      "rotr-comp-cloudleaper",
      "rotr-evo-cloudleaper"
    ],
    "npcOwner": "volta",
    "lore": "Storm Control is taught in the Living World before Keepers chase mythic hunts.",
    "archetype": "Tempo",
    "kind": "starter"
  },
  {
    "id": "starter-earth",
    "name": "Earth Guardian",
    "strategy": "Walls and Locations; win long.",
    "difficulty": "easy",
    "strengths": [
      "survivability"
    ],
    "weaknesses": [
      "slow starts"
    ],
    "cards": {
      "rotr-c-basaltpup": 2,
      "rotr-c-canyonbeetle": 2,
      "rotr-c-crystowl": 2,
      "rotr-c-fossilhound": 2,
      "rotr-c-gritling": 2,
      "rotr-c-hearthstone": 2,
      "rotr-c-pebblit": 2,
      "rotr-c-quartzhorn": 2,
      "rotr-c-rubblefin": 2,
      "rotr-c-shalehorn": 2,
      "rotr-c-stonegrub": 2,
      "rotr-c-pebble-guard": 2,
      "rotr-s-stone-brace": 2,
      "rotr-s-quake-tap": 2,
      "rotr-s-item-stone-steady-draught": 2,
      "rotr-s-item-healing-stone": 2,
      "rotr-s-item-stone-crash": 2,
      "rotr-s-item-stone-guard": 2,
      "rotr-comp-basaltpup": 2,
      "rotr-comp-canyonbeetle": 2,
      "rotr-comp-crystowl": 2,
      "rotr-comp-fossilhound": 2,
      "rotr-comp-gritling": 2,
      "rotr-comp-hearthstone": 2,
      "rotr-comp-pebblit": 2,
      "rotr-comp-quartzhorn": 2,
      "rotr-comp-rubblefin": 2,
      "rotr-comp-shalehorn": 2,
      "rotr-comp-stonegrub": 2,
      "rotr-e-keeper-s-satchel": 2,
      "rotr-e-item-smooth-stone-claw": 2,
      "rotr-e-item-training-tail-ring": 2,
      "rotr-e-item-cloth-battle-harness": 2,
      "rotr-e-item-simple-horncap": 2
    },
    "recommendedUpgrades": [
      "rotr-c-basaltpup",
      "rotr-comp-basaltpup",
      "rotr-evo-basaltpup"
    ],
    "npcOwner": "basalt",
    "lore": "Earth Guardian is taught in the Living World before Keepers chase mythic hunts.",
    "archetype": "Control",
    "kind": "starter"
  },
  {
    "id": "starter-crystal",
    "name": "Crystal Mage",
    "strategy": "Shatter interaction and spell density.",
    "difficulty": "medium",
    "strengths": [
      "synergy"
    ],
    "weaknesses": [
      "hate cards"
    ],
    "cards": {
      "rotr-c-shard-bit": 2,
      "rotr-s-crystal-ping": 2,
      "rotr-e-keeper-s-satchel": 2,
      "rotr-e-crystal-lens": 2,
      "rotr-e-item-training-tail-ring": 2,
      "rotr-e-item-cloth-battle-harness": 2,
      "rotr-e-item-celestial-riftblade": 2,
      "rotr-e-item-crown-of-ten-affinities": 2,
      "rotr-e-item-cloth-pet-vest": 2,
      "rotr-e-item-simple-headband": 2,
      "rotr-e-item-training-paw-wraps": 2,
      "rotr-e-item-armor-of-the-rift-guardian": 2,
      "rotr-e-item-linen-ear-hood": 2,
      "rotr-e-item-soft-tail-sleeve": 2,
      "rotr-r-mat-wood-fiber": 2,
      "rotr-r-mat-smooth-stone": 2,
      "rotr-r-mat-basic-cloth": 2,
      "rotr-r-mat-clear-water": 2
    },
    "recommendedUpgrades": [
      "rotr-s-crystal-ping",
      "rotr-e-crystal-lens",
      "rotr-x-prism-noon"
    ],
    "npcOwner": "solen",
    "lore": "Crystal Mage is taught in the Living World before Keepers chase mythic hunts.",
    "archetype": "Spell midrange",
    "kind": "starter"
  },
  {
    "id": "starter-shadow",
    "name": "Shadow Corruption",
    "strategy": "Corrupt Residue into void finishers.",
    "difficulty": "hard",
    "strengths": [
      "synergy"
    ],
    "weaknesses": [
      "hate cards"
    ],
    "cards": {
      "rotr-c-dusk-mote": 2,
      "rotr-s-shade-tax": 2,
      "rotr-s-corrupt-whisper": 2,
      "rotr-e-keeper-s-satchel": 2,
      "rotr-e-shade-mantle": 2,
      "rotr-e-item-training-tail-ring": 2,
      "rotr-e-item-cloth-battle-harness": 2,
      "rotr-e-item-celestial-riftblade": 2,
      "rotr-e-item-crown-of-ten-affinities": 2,
      "rotr-e-item-cloth-pet-vest": 2,
      "rotr-e-item-simple-headband": 2,
      "rotr-e-item-training-paw-wraps": 2,
      "rotr-e-item-armor-of-the-rift-guardian": 2,
      "rotr-e-item-linen-ear-hood": 2,
      "rotr-e-item-soft-tail-sleeve": 2,
      "rotr-r-mat-wood-fiber": 2,
      "rotr-r-mat-smooth-stone": 2,
      "rotr-r-mat-basic-cloth": 2,
      "rotr-r-mat-clear-water": 2
    },
    "recommendedUpgrades": [
      "rotr-s-shade-tax",
      "rotr-s-corrupt-whisper",
      "rotr-e-shade-mantle"
    ],
    "npcOwner": "nyx",
    "lore": "Shadow Corruption is taught in the Living World before Keepers chase mythic hunts.",
    "archetype": "Attrition",
    "kind": "starter"
  },
  {
    "id": "starter-light",
    "name": "Light Protection",
    "strategy": "Ward walls and Harmony heals.",
    "difficulty": "medium",
    "strengths": [
      "synergy"
    ],
    "weaknesses": [
      "hate cards"
    ],
    "cards": {
      "rotr-c-auralynx": 2,
      "rotr-c-celestora": 2,
      "rotr-c-citadelmoth": 2,
      "rotr-c-dawnkit": 2,
      "rotr-c-gleamhare": 2,
      "rotr-c-glimmerp": 2,
      "rotr-c-lightspire": 2,
      "rotr-c-luminara": 2,
      "rotr-c-prismoth": 2,
      "rotr-c-radiantkit": 2,
      "rotr-c-solfinch": 2,
      "rotr-c-lantern-acolyte": 2,
      "rotr-s-lantern-lift": 2,
      "rotr-s-festival-cheer": 2,
      "rotr-s-item-radiant-recovery-flask": 1,
      "rotr-s-item-celestial-renewal": 2,
      "rotr-s-item-aurora-treat": 2,
      "rotr-s-item-starlit-lullaby-charm": 2,
      "rotr-comp-auralynx": 2,
      "rotr-comp-celestora": 2,
      "rotr-comp-citadelmoth": 2,
      "rotr-comp-dawnkit": 2,
      "rotr-comp-gleamhare": 2,
      "rotr-comp-glimmerp": 2,
      "rotr-comp-lightspire": 2,
      "rotr-comp-luminara": 2,
      "rotr-comp-prismoth": 2,
      "rotr-comp-radiantkit": 2,
      "rotr-comp-solfinch": 2,
      "rotr-e-keeper-s-satchel": 2,
      "rotr-e-lantern-badge": 2,
      "rotr-e-item-training-tail-ring": 2,
      "rotr-e-item-cloth-battle-harness": 2,
      "rotr-e-item-radiant-sun-disk": 2
    },
    "recommendedUpgrades": [
      "rotr-c-auralynx",
      "rotr-comp-auralynx",
      "rotr-evo-auralynx"
    ],
    "npcOwner": "lumen",
    "lore": "Light Protection is taught in the Living World before Keepers chase mythic hunts.",
    "archetype": "Midrange",
    "kind": "starter"
  },
  {
    "id": "starter-spirit",
    "name": "Spirit Combo",
    "strategy": "Echo loops with soft engines.",
    "difficulty": "hard",
    "strengths": [
      "synergy"
    ],
    "weaknesses": [
      "hate cards"
    ],
    "cards": {
      "rotr-c-dreamhare": 2,
      "rotr-c-ghostbloom": 2,
      "rotr-c-lanternjay": 2,
      "rotr-c-marshloom": 2,
      "rotr-c-riftpup": 2,
      "rotr-c-soulmoth": 2,
      "rotr-c-starveil": 2,
      "rotr-c-wispdeer": 2,
      "rotr-c-wisplet": 2,
      "rotr-c-spirit-moth": 2,
      "rotr-s-spirit-echo": 2,
      "rotr-s-item-spirit-renewal-potion": 2,
      "rotr-s-item-focus-tonic": 2,
      "rotr-s-item-spirit-charge": 2,
      "rotr-s-item-medicine-pack": 2,
      "rotr-comp-dreamhare": 2,
      "rotr-comp-ghostbloom": 2,
      "rotr-comp-lanternjay": 2,
      "rotr-comp-marshloom": 2,
      "rotr-comp-riftpup": 2,
      "rotr-comp-soulmoth": 2,
      "rotr-comp-starveil": 2,
      "rotr-comp-wispdeer": 2,
      "rotr-comp-wisplet": 2,
      "rotr-e-keeper-s-satchel": 2,
      "rotr-e-item-training-tail-ring": 2,
      "rotr-e-item-basic-focus-orb": 2,
      "rotr-e-item-cloth-battle-harness": 2,
      "rotr-e-item-spirit-glow-orb": 2,
      "rotr-e-item-spiritfire-lantern": 2,
      "rotr-e-item-celestial-riftblade": 2
    },
    "recommendedUpgrades": [
      "rotr-c-dreamhare",
      "rotr-comp-dreamhare",
      "rotr-evo-dreamhare"
    ],
    "npcOwner": "solen",
    "lore": "Spirit Combo is taught in the Living World before Keepers chase mythic hunts.",
    "archetype": "Combo",
    "kind": "starter"
  },
  {
    "id": "starter-celestial",
    "name": "Celestial Legends",
    "strategy": "Ramp to Ancient Awaken payoffs.",
    "difficulty": "expert",
    "strengths": [
      "synergy"
    ],
    "weaknesses": [
      "hate cards"
    ],
    "cards": {
      "rotr-c-star-midge": 2,
      "rotr-s-star-dust": 2,
      "rotr-e-keeper-s-satchel": 2,
      "rotr-e-item-training-tail-ring": 2,
      "rotr-e-item-cloth-battle-harness": 2,
      "rotr-e-item-celestial-riftblade": 2,
      "rotr-e-item-crown-of-ten-affinities": 2,
      "rotr-e-item-cloth-pet-vest": 2,
      "rotr-e-item-simple-headband": 2,
      "rotr-e-item-training-paw-wraps": 2,
      "rotr-e-item-armor-of-the-rift-guardian": 2,
      "rotr-e-item-linen-ear-hood": 2,
      "rotr-e-item-soft-tail-sleeve": 2,
      "rotr-r-mat-wood-fiber": 2,
      "rotr-r-mat-smooth-stone": 2,
      "rotr-r-mat-basic-cloth": 2,
      "rotr-r-mat-clear-water": 2,
      "rotr-r-mat-wild-herbs": 2
    },
    "recommendedUpgrades": [
      "rotr-s-star-dust",
      "rotr-r-mat-celestial-star-fragment",
      "rotr-l-region-celestial-rift"
    ],
    "npcOwner": "astral",
    "lore": "Celestial Legends is taught in the Living World before Keepers chase mythic hunts.",
    "archetype": "Ramp",
    "kind": "starter"
  },
  {
    "id": "npc-mira",
    "name": "Mira's Care Deck",
    "strategy": "Teaching deck for new Keepers.",
    "difficulty": "easy",
    "strengths": [
      "synergy"
    ],
    "weaknesses": [
      "hate cards"
    ],
    "cards": {
      "rotr-c-auralynx": 2,
      "rotr-c-celestora": 2,
      "rotr-c-citadelmoth": 2,
      "rotr-c-dawnkit": 2,
      "rotr-c-gleamhare": 2,
      "rotr-c-glimmerp": 2,
      "rotr-c-lightspire": 2,
      "rotr-c-luminara": 2,
      "rotr-c-prismoth": 2,
      "rotr-c-radiantkit": 2,
      "rotr-c-solfinch": 2,
      "rotr-c-lantern-acolyte": 2,
      "rotr-s-lantern-lift": 2,
      "rotr-s-festival-cheer": 2,
      "rotr-s-item-radiant-recovery-flask": 1,
      "rotr-s-item-celestial-renewal": 2,
      "rotr-s-item-aurora-treat": 2,
      "rotr-s-item-starlit-lullaby-charm": 2,
      "rotr-comp-auralynx": 2,
      "rotr-comp-celestora": 2,
      "rotr-comp-citadelmoth": 2,
      "rotr-comp-dawnkit": 2,
      "rotr-comp-gleamhare": 2,
      "rotr-comp-glimmerp": 2,
      "rotr-comp-lightspire": 2,
      "rotr-comp-luminara": 2,
      "rotr-comp-prismoth": 2,
      "rotr-comp-radiantkit": 2,
      "rotr-comp-solfinch": 2,
      "rotr-e-keeper-s-satchel": 2,
      "rotr-e-lantern-badge": 2,
      "rotr-e-item-training-tail-ring": 2,
      "rotr-e-item-cloth-battle-harness": 2,
      "rotr-e-item-radiant-sun-disk": 2
    },
    "recommendedUpgrades": [
      "rotr-c-auralynx",
      "rotr-comp-auralynx",
      "rotr-evo-auralynx"
    ],
    "npcOwner": "mira",
    "lore": "Mira's Care Deck is taught in the Living World before Keepers chase mythic hunts.",
    "archetype": "Teach",
    "kind": "npc"
  },
  {
    "id": "npc-blacksmith",
    "name": "Kael's Temper Deck",
    "strategy": "Equipment-forward forge lesson.",
    "difficulty": "medium",
    "strengths": [
      "fast pressure"
    ],
    "weaknesses": [
      "late game"
    ],
    "cards": {
      "rotr-c-ashwing": 2,
      "rotr-c-cindercub": 2,
      "rotr-c-cinderquill": 2,
      "rotr-c-craterhorn": 2,
      "rotr-c-emberfox": 2,
      "rotr-c-embernewt": 2,
      "rotr-c-furnacebeetle": 2,
      "rotr-c-lavaling": 2,
      "rotr-c-pyrespore": 2,
      "rotr-c-slagpup": 2,
      "rotr-c-ash-urchin": 2,
      "rotr-s-ember-spark": 2,
      "rotr-s-forge-temper": 2,
      "rotr-s-item-riftberry-tonic": 2,
      "rotr-s-item-emberheart-elixir": 2,
      "rotr-s-item-spark-healing-draught": 2,
      "rotr-s-item-ember-soothe-balm": 2,
      "rotr-comp-ashwing": 2,
      "rotr-comp-cindercub": 2,
      "rotr-comp-cinderquill": 2,
      "rotr-comp-craterhorn": 2,
      "rotr-comp-emberfox": 2,
      "rotr-comp-embernewt": 2,
      "rotr-comp-furnacebeetle": 2,
      "rotr-comp-lavaling": 2,
      "rotr-comp-pyrespore": 2,
      "rotr-comp-slagpup": 2,
      "rotr-e-keeper-s-satchel": 2,
      "rotr-e-ember-collar": 2,
      "rotr-e-item-training-tail-ring": 2,
      "rotr-e-item-cloth-battle-harness": 2,
      "rotr-e-item-ember-talons": 2,
      "rotr-e-item-ashfang-talons": 2
    },
    "recommendedUpgrades": [
      "rotr-c-ashwing",
      "rotr-comp-ashwing",
      "rotr-evo-ashwing"
    ],
    "npcOwner": "kael",
    "lore": "Kael's Temper Deck is taught in the Living World before Keepers chase mythic hunts.",
    "archetype": "Equipment",
    "kind": "npc"
  }
]
