{
  "pageNumber": 15,
  "storyPageNumber": 11,
  "bookRole": "story",
  "title": "Mirror Case",
  "storyPurpose": "Memory mirrors show Nira meeting Meridian; Mira nearly convinced.",
  "layout": {
    "type": "three-stack",
    "panelCount": 3
  },
  "panels": [
    {
      "id": "p11a",
      "description": "Cracked memory mirrors flare; false image of Nira meeting Meridian agents with transmission token.",
      "bubbles": [
        {
          "kind": "sfx",
          "text": "MIRROR-HISS",
          "x": 50,
          "y": 25,
          "tail": null,
          "maxWidthPct": 34,
          "readOrder": 0
        },
        {
          "kind": "speech",
          "text": "There. That's you.",
          "x": 40,
          "y": 70,
          "tail": "up",
          "maxWidthPct": 34,
          "speaker": "Mira Eggwarden",
          "readOrder": 1
        }
      ]
    },
    {
      "id": "p11b",
      "description": "Nira Quill: uncertain hunter, lean, weather cloak, quill-knife kit, conflicted eyes shaking head; Bramblefox snarls at mirror not at her.",
      "bubbles": [
        {
          "kind": "speech",
          "text": "I met them to steal files — not feed them.",
          "x": 50,
          "y": 35,
          "tail": "down",
          "maxWidthPct": 40,
          "speaker": "Nira Quill",
          "readOrder": 2
        },
        {
          "kind": "creature",
          "text": "*false-scent*",
          "x": 65,
          "y": 70,
          "tail": "up",
          "maxWidthPct": 34,
          "speaker": "Bramblefox",
          "readOrder": 3
        }
      ]
    },
    {
      "id": "p11c",
      "description": "Mira Eggwarden: young adult Hatchery mentor/Keeper, warm brown skin, dark hair in practical braid, travel-stained hatchery coat over Compact robes, Compact lantern charm on satchel, determined protective eyes hurt-closed expression; egg dim; Spark distressed between Mira and Nira.",
      "bubbles": [
        {
          "kind": "thought",
          "text": "If she's lying, I've already failed them.",
          "x": 50,
          "y": 40,
          "tail": null,
          "maxWidthPct": 40,
          "speaker": "Mira Eggwarden",
          "readOrder": 4
        }
      ]
    }
  ],
  "dialogue": [
    {
      "panelId": "p11a",
      "kind": "speech",
      "text": "There. That's you.",
      "x": 40,
      "y": 70,
      "tail": "up",
      "maxWidthPct": 34,
      "speaker": "Mira Eggwarden",
      "readOrder": 1
    },
    {
      "panelId": "p11b",
      "kind": "speech",
      "text": "I met them to steal files — not feed them.",
      "x": 50,
      "y": 35,
      "tail": "down",
      "maxWidthPct": 40,
      "speaker": "Nira Quill",
      "readOrder": 2
    },
    {
      "panelId": "p11b",
      "kind": "creature",
      "text": "*false-scent*",
      "x": 65,
      "y": 70,
      "tail": "up",
      "maxWidthPct": 34,
      "speaker": "Bramblefox",
      "readOrder": 3
    },
    {
      "panelId": "p11c",
      "kind": "thought",
      "text": "If she's lying, I've already failed them.",
      "x": 50,
      "y": 40,
      "tail": null,
      "maxWidthPct": 40,
      "speaker": "Mira Eggwarden",
      "readOrder": 4
    }
  ],
  "captions": [],
  "soundEffects": [
    {
      "panelId": "p11a",
      "kind": "sfx",
      "text": "MIRROR-HISS",
      "x": 50,
      "y": 25,
      "tail": null,
      "maxWidthPct": 34,
      "readOrder": 0
    }
  ],
  "characters": [
    "mira-eggwarden",
    "nira-quill"
  ],
  "creatures": [
    "spark",
    "bramblefox",
    "wisplet",
    "dormant-egg"
  ],
  "locations": [
    "Traitor's Gate — Memory Mirrors"
  ],
  "artifacts": [],
  "continuity": {
    "mirrors": "false-nira",
    "mira": "nearly-convinced"
  },
  "requiredMoments": [
    10,
    2
  ],
  "grokPrompt": "Original high-energy Western fantasy comic storytelling with dynamic panel composition, dramatic inked linework, richly painted colors, expressive character acting, and clear cinematic action. Original Riftwilds IP only. Black stone, pale silver metal, moss and timber first; cyan Rift light, deep red warning runes, restrained violet gate shimmer as accents only. NO purple AI-fantasy neon default. NO Marvel/DC/Pokémon characters or logos. Riftwilds comic \"The Traitor's Gate\" Issue #7, STORY PAGE 11/25 — Mirror Case. Story purpose: Memory mirrors show Nira meeting Meridian; Mira nearly convinced. Layout: three-stack. 3 panels with clear inked gutters. Panel 1 (p11a): Cracked memory mirrors flare; false image of Nira meeting Meridian agents with transmission token. Panel 2 (p11b): Nira Quill: uncertain hunter, lean, weather cloak, quill-knife kit, conflicted eyes shaking head; Bramblefox snarls at mirror not at her. Panel 3 (p11c): Mira Eggwarden: young adult Hatchery mentor/Keeper, warm brown skin, dark hair in practical braid, travel-stained hatchery coat over Compact robes, Compact lantern charm on satchel, determined protective eyes hurt-closed expression; egg dim; Spark distressed between Mira and Nira. Characters: mira-eggwarden, nira-quill. Creatures: spark, bramblefox, wisplet, dormant-egg. Spark design lock: Spark the Glowpup-line Riftborn hatchling: soft luminous fur, cyan-gold rift markings, large expressive eyes, small crystal growths, glowing-tip emotional tail, steadier aura when bonded; cute but original — not a franchise mascot. Keeper lock: Mira Eggwarden: young adult Hatchery mentor/Keeper, warm brown skin, dark hair in practical braid, travel-stained hatchery coat over Compact robes, Compact lantern charm on satchel, determined protective eyes. Egg lock: dormant Riftborn egg: warm oval shell with cyan-amber seam markings, soft pulse glow, no full hatch — visually identical across pages. Oathwarden lock: Oathwarden Seraph: tall ceremonial black-and-silver armor, split judgment mask, cyan oath flame, long judgment spear, broken Keeper cloak, floating lock rings, one armor side corrupted, orbiting memory mirrors. Environment: Traitor Gate approaches. Time: day. Lighting: black stone with cyan rift accents. Continuity: {\"mirrors\": \"false-nira\", \"mira\": \"nearly-convinced\"} Leave empty balloon-safe and narration-safe negative space in upper/lower panel corners. NO readable text of any kind in the artwork.",
  "negativePrompt": "readable dialogue text, captions, logos, watermarks, page numbers, UI chrome, Marvel, DC, Pokémon, manga screentone trademarks, extra limbs, duplicate characters, missing companions, purple neon fantasy default, photoreal modern clothing, Pikachu lookalike, Cal Reed, Voltkit",
  "pageTurnObjective": "Wisplet enters.",
  "letteringInstructions": "Standard speech + narration; keep tails off faces and Spark's eyes; Gate text formal.",
  "generationStatus": "seeded",
  "letteringStatus": "ok",
  "approvalStatus": "script-complete",
  "artAlt": "Mirror Case — The Traitor's Gate page 11",
  "atmosphere": "rift",
  "transcript": [
    "SFX: MIRROR-HISS",
    "SPEECH (Mira Eggwarden): There. That's you.",
    "SPEECH (Nira Quill): I met them to steal files — not feed them.",
    "CREATURE (Bramblefox): *false-scent*",
    "THOUGHT (Mira Eggwarden): If she's lying, I've already failed them."
  ],
  "a11yTranscript": [
    "SFX: MIRROR-HISS",
    "SPEECH (Mira Eggwarden): There. That's you.",
    "SPEECH (Nira Quill): I met them to steal files — not feed them.",
    "CREATURE (Bramblefox): *false-scent*",
    "THOUGHT (Mira Eggwarden): If she's lying, I've already failed them."
  ],
  "codexLinks": [],
  "cardTeases": [],
  "id": "the-traitors-gate-issue-007-p015",
  "cleanArtRel": "generated/raw-art/page-015.webp",
  "letteredArtRel": "generated/lettered-pages/page-015.webp",
  "publicArtRel": "assets/comics/the-traitors-gate/issue-007/pages/page-015.webp",
  "bakedLettering": true,
  "composedPlate": true
}
