{
  "id": "forgekeeper-vessa",
  "slug": "forgekeeper-vessa",
  "regionId": "ember-crater",
  "paths": {
    "portrait": "/assets/npcs/ember-crater/forgekeeper-vessa/portrait.png",
    "fullBody": "/assets/npcs/ember-crater/forgekeeper-vessa/full-body.png",
    "sprite": "/assets/npcs/ember-crater/forgekeeper-vessa/sprite.png",
    "thumbnail": "/assets/npcs/ember-crater/forgekeeper-vessa/thumbnail.png"
  },
  "assets": {
    "portrait": true,
    "fullBodyDistinct": true,
    "fullBodyPresent": true,
    "spriteDistinct": false,
    "spritePresent": true,
    "thumbnail": true
  },
  "artStatus": "generated",
  "updatedAt": "2026-07-17T23:20:13.063Z",
  "derivedAt": "2026-07-18T05:18:33.491Z",
  "fullBodyDistinct": false,
  "spriteDistinct": false,
  "note": "Portrait generated; full-body/sprite derived from portrait pending dedicated sheets"
}
